mongrel_transferrer/__init__.py
mongrel_transferrer/mongrel/__init__.py
mongrel_transferrer/mongrel/helpers/__init__.py
mongrel_transferrer/mongrel/helpers/constants.py
mongrel_transferrer/mongrel/helpers/conversions.py
mongrel_transferrer/mongrel/helpers/database_functions.py
mongrel_transferrer/mongrel/helpers/exceptions.py
mongrel_transferrer/mongrel/helpers/map_flattener.py
mongrel_transferrer/mongrel/helpers/utils.py
mongrel_transferrer/mongrel/helpers/types/__init__.py
mongrel_transferrer/mongrel/helpers/types/bloom_filter.py
mongrel_transferrer/mongrel/helpers/types/column_info.py
mongrel_transferrer/mongrel/helpers/types/data_type.py
mongrel_transferrer/mongrel/helpers/types/relation.py
mongrel_transferrer/mongrel/helpers/types/relation_type.py
mongrel_transferrer/mongrel/objects/__init__.py
mongrel_transferrer/mongrel/objects/enums.py
mongrel_transferrer/mongrel/objects/relation_builder.py
mongrel_transferrer/mongrel/objects/table.py
mongrel_transferrer/mongrel/objects/table_builder.py
mongrel_transferrer/mongrel/objects/transferrer.py
mongrel_transferrer/mongrel/relation_discovery/__init__.py
mongrel_transferrer/mongrel/relation_discovery/configuration_builder.py
mongrel_transferrer/mongrel/relation_discovery/relation_discovery.py
mongrel_transferrer-0.1.0.dist-info/LICENSE
mongrel_transferrer-0.1.0.dist-info/METADATA
mongrel_transferrer-0.1.0.dist-info/WHEEL
mongrel_transferrer-0.1.0.dist-info/top_level.txt
mongrel_transferrer-0.1.0.dist-info/RECORD
