Metadata-Version: 2.1
Name: mongrel_transferrer
Version: 0.1.0
Summary: MONGREL is a tool that allows hierarchical datastructures like MongoDB to be ported to relational datastructures like PostgreSQL.
Author-email: Ricardo Prida <mail.prida@gmail.com>
Project-URL: Homepage, https://github.com/PrRicardo/Mongrel
Project-URL: Issues, https://github.com/PrRicardo/Mongrel/issues
Classifier: Programming Language :: Python :: 3
Classifier: License :: OSI Approved :: GNU General Public License v3 (GPLv3)
Classifier: Operating System :: OS Independent
Requires-Python: >=3.9
License-File: LICENSE
Requires-Dist: pandas ~=2.2.2
Requires-Dist: pymongo ~=4.8.0
Requires-Dist: sqlalchemy ~=2.0.27
Requires-Dist: tqdm ~=4.66.2
Requires-Dist: psycopg2-binary ~=2.9.9
Requires-Dist: mmh3 ~=4.1.0
